grpc_framework/__init__.py
grpc_framework/application.py
grpc_framework/config.py
grpc_framework/exceptions.py
grpc_framework/types.py
grpc_framework/client/__init__.py
grpc_framework/client/channel_pool_manager.py
grpc_framework/client/grpc_client.py
grpc_framework/core/__init__.py
grpc_framework/core/error_handler.py
grpc_framework/core/service.py
grpc_framework/core/adaptor/__init__.py
grpc_framework/core/adaptor/domain.py
grpc_framework/core/adaptor/grpc_adaptor.py
grpc_framework/core/adaptor/request_adaptor.py
grpc_framework/core/adaptor/response_adaptor.py
grpc_framework/core/context/__init__.py
grpc_framework/core/context/request_context_manager.py
grpc_framework/core/di/__init__.py
grpc_framework/core/di/container.py
grpc_framework/core/di/depends.py
grpc_framework/core/di/provider.py
grpc_framework/core/enums/__init__.py
grpc_framework/core/enums/grpc.py
grpc_framework/core/interceptors/__init__.py
grpc_framework/core/interceptors/request_context_interceptor.py
grpc_framework/core/lifecycle/__init__.py
grpc_framework/core/lifecycle/lifecycle.py
grpc_framework/core/middleware/__init__.py
grpc_framework/core/middleware/middleware.py
grpc_framework/core/params/__init__.py
grpc_framework/core/params/domain.py
grpc_framework/core/params/utils.py
grpc_framework/core/request/__init__.py
grpc_framework/core/request/request.py
grpc_framework/core/response/__init__.py
grpc_framework/core/response/response.py
grpc_framework/core/serialization/__init__.py
grpc_framework/core/serialization/codec_impls.py
grpc_framework/core/serialization/converter_impls.py
grpc_framework/core/serialization/interface.py
grpc_framework/utils/__init__.py
grpc_framework/utils/config_parser.py
grpc_framework/utils/logger.py
grpc_framework/utils/reactive_context.py
grpc_framework/utils/symbol_by_name.py
grpc_framework/utils/sync2async_utils.py
grpc_framework-0.3.2b0.dist-info/licenses/LICENSE
grpc_framework-0.3.2b0.dist-info/METADATA
grpc_framework-0.3.2b0.dist-info/WHEEL
grpc_framework-0.3.2b0.dist-info/top_level.txt
grpc_framework-0.3.2b0.dist-info/RECORD
