Metadata-Version: 2.4
Name: grpc-framework
Version: 0.3.2b0
Summary: Easy gRPC APIs Framework.
Author: surp1us
License: MIT License
Project-URL: Homepage, https://github.com/JokerCrying/grpc-framework
Project-URL: Repository, https://github.com/JokerCrying/grpc-framework
Project-URL: Bug Tracker, https://github.com/JokerCrying/grpc-framework/issues
Keywords: grpc,framework,grpcio
Classifier: Development Status :: 3 - Alpha
Classifier: Intended Audience :: Developers
Classifier: License :: OSI Approved :: MIT License
Classifier: Programming Language :: Python :: 3
Classifier: Programming Language :: Python :: 3.7
Classifier: Programming Language :: Python :: 3.8
Classifier: Programming Language :: Python :: 3.9
Classifier: Programming Language :: Python :: 3.10
Classifier: Programming Language :: Python :: 3.11
Classifier: Programming Language :: Python :: 3.12
Classifier: Programming Language :: Python :: 3.13
Requires-Python: >=3.7
License-File: LICENSE
Requires-Dist: grpcio<2.0,>=1.73.1
Requires-Dist: grpcio-reflection<2.0,>=1.73.1
Requires-Dist: protobuf<7.0,>=6.31.1
Requires-Dist: PyYAML<7.0,>=6.0.3
Requires-Dist: grpcio-health-checking<2.0,>=1.73.1
Requires-Dist: grpcio-tools<2.0,>=1.73.1
Provides-Extra: dev
Requires-Dist: pytest>=6.0; extra == "dev"
Requires-Dist: pytest-asyncio; extra == "dev"
Requires-Dist: black; extra == "dev"
Requires-Dist: flake8; extra == "dev"
Requires-Dist: mypy; extra == "dev"
Provides-Extra: docs
Requires-Dist: sphinx; extra == "docs"
Requires-Dist: sphinx-rtd-theme; extra == "docs"
Dynamic: license-file
